spawn_py/__init__.py
spawn_py/bind_to_events.py
spawn_py/client.py
spawn_py-0.1.0.dist-info/LICENSE
spawn_py-0.1.0.dist-info/METADATA
spawn_py-0.1.0.dist-info/WHEEL
spawn_py-0.1.0.dist-info/RECORD
