Metadata-Version: 2.1
Name: spawn-py
Version: 0.1.0
Summary: A python package to work with the Spawn API
Author: Benjamin Trom
Author-email: benjamintrom@gmail.com
Requires-Python: >=3.8,<4.0
Classifier: Programming Language :: Python :: 3
Classifier: Programming Language :: Python :: 3.8
Classifier: Programming Language :: Python :: 3.9
Classifier: Programming Language :: Python :: 3.10
Classifier: Programming Language :: Python :: 3.11
Requires-Dist: postgrest-py (>=0.10.3,<0.11.0)
Requires-Dist: python-dotenv (>=0.21.1,<0.22.0)
Requires-Dist: websockets (>=10.4,<11.0)
